<SO><y>304</y><x>1955</x><d>0</d><cT>Platform</cT><sT>21</sT></SO>
<SO><y>304</y><x>1772</x><d>1</d><cT>Platform</cT><sT>20</sT></SO>
<SO><addProps><dir>1</dir><start>0</start><range>5</range><axis>_x</axis><switchCode>4</switchCode></addProps><y>306</y><x>1264</x><d>2</d><cT>MoveablePlatform</cT><sT>0</sT></SO>
<SO><addProps><dir>1</dir><start>0</start><range>5</range><axis>_x</axis><switchCode>3</switchCode></addProps><y>301</y><x>985</x><d>3</d><cT>MoveablePlatform</cT><sT>2</sT></SO>
<SO><y>296</y><x>-16</x><d>4</d><cT>Platform</cT><sT>23</sT></SO>
<SO><y>296</y><x>176</x><d>5</d><cT>Platform</cT><sT>23</sT></SO>
<SO><y>296</y><x>368</x><d>6</d><cT>Platform</cT><sT>22</sT></SO>
<SO><y>168</y><x>-32</x><d>7</d><cT>Platform</cT><sT>23</sT></SO>
<SO><y>168</y><x>160</x><d>8</d><cT>Platform</cT><sT>23</sT></SO>
<SO><y>168</y><x>352</x><d>9</d><cT>Platform</cT><sT>23</sT></SO>
<SO><addProps><switchCode>1</switchCode></addProps><y>168</y><x>208</x><d>10</d><cT>Switch</cT><sT>0</sT></SO>
<SO><addProps><dir>1</dir><start>0</start><range>6</range><axis>_y</axis><switchCode>1</switchCode></addProps><y>301</y><x>377</x><d>11</d><cT>MoveablePlatform</cT><sT>0</sT></SO>
<SO><y>296</y><x>440</x><d>12</d><cT>Platform</cT><sT>21</sT></SO>
<SO><y>296</y><x>640</x><d>13</d><cT>Platform</cT><sT>23</sT></SO>
<SO><y>168</y><x>736</x><d>14</d><cT>Platform</cT><sT>23</sT></SO>
<SO><y>168</y><x>928</x><d>15</d><cT>Platform</cT><sT>23</sT></SO>
<SO><y>296</y><x>832</x><d>16</d><cT>Platform</cT><sT>22</sT></SO>
<SO><y>296</y><x>902</x><d>17</d><cT>Platform</cT><sT>21</sT></SO>
<SO><addProps><dir>-1</dir><start>0</start><range>4</range><axis>_y</axis><switchCode>2</switchCode></addProps><y>301</y><x>839</x><d>18</d><cT>MoveablePlatform</cT><sT>1</sT></SO>
<SO><y>296</y><x>910</x><d>19</d><cT>Platform</cT><sT>20</sT></SO>
<SO><y>296</y><x>976</x><d>20</d><cT>Platform</cT><sT>20</sT></SO>
<SO><y>296</y><x>1040</x><d>21</d><cT>Platform</cT><sT>22</sT></SO>
<SO><y>168</y><x>1120</x><d>22</d><cT>Platform</cT><sT>23</sT></SO>
<SO><y>296</y><x>1136</x><d>23</d><cT>Platform</cT><sT>23</sT></SO>
<SO><y>296</y><x>1128</x><d>24</d><cT>Platform</cT><sT>21</sT></SO>
<SO><y>168</y><x>1312</x><d>25</d><cT>Platform</cT><sT>23</sT></SO>
<SO><y>296</y><x>1328</x><d>26</d><cT>Platform</cT><sT>22</sT></SO>
<SO><y>296</y><x>1400</x><d>27</d><cT>Platform</cT><sT>23</sT></SO>
<SO><y>296</y><x>1392</x><d>28</d><cT>Platform</cT><sT>21</sT></SO>
<SO><y>296</y><x>1624</x><d>29</d><cT>Platform</cT><sT>22</sT></SO>
<SO><y>168</y><x>1680</x><d>30</d><cT>Platform</cT><sT>23</sT></SO>
<SO><addProps><dir>1</dir><start>0</start><range>5</range><axis>_x</axis><switchCode>4</switchCode></addProps><y>296</y><x>1632</x><d>31</d><cT>MoveablePlatform</cT><sT>0</sT></SO>
<SO><addProps><dir>1</dir><start>0</start><range>10</range><axis>_y</axis><switchCode>5</switchCode></addProps><y>255</y><x>1886</x><d>32</d><cT>MoveablePlatform</cT><sT>2</sT></SO>
<SO><addProps><switchCode>4</switchCode></addProps><y>296</y><x>1266</x><d>33</d><cT>Switch</cT><sT>0</sT></SO>
<SO><y>168</y><x>1872</x><d>34</d><cT>Platform</cT><sT>22</sT></SO>
<SO><y>304</y><x>2019</x><d>35</d><cT>Platform</cT><sT>23</sT></SO>
<SO><y>296</y><x>448</x><d>36</d><cT>Platform</cT><sT>23</sT></SO>
<SO><y>304</y><x>1742</x><d>37</d><cT>Platform</cT><sT>20</sT></SO>
<SO><y>304</y><x>1836</x><d>38</d><cT>Platform</cT><sT>22</sT></SO>
<SO><y>304</y><x>1734</x><d>39</d><cT>Platform</cT><sT>21</sT></SO>
<SO><y>304</y><x>1814</x><d>40</d><cT>Platform</cT><sT>20</sT></SO>
<SO><y>304</y><x>1963</x><d>41</d><cT>Platform</cT><sT>20</sT></SO>
<SO><y>304</y><x>2211</x><d>42</d><cT>Platform</cT><sT>22</sT></SO>
<SO><addProps><dir>1</dir><start>0</start><range>4</range><axis>_x</axis><switchCode>10</switchCode></addProps><y>304</y><x>2219</x><d>43</d><cT>MoveablePlatform</cT><sT>2</sT></SO>
<SO><y>296</y><x>1560</x><d>44</d><cT>Platform</cT><sT>20</sT></SO>
<SO><y>168</y><x>1488</x><d>45</d><cT>Platform</cT><sT>23</sT></SO>
<SO><addProps><switchCode>5</switchCode></addProps><y>304</y><x>1753</x><d>46</d><cT>Switch</cT><sT>1</sT></SO>
<SO><y>223</y><x>2429</x><d>47</d><cT>Goal</cT><sT>1</sT></SO>
<SO><y>304</y><x>2355</x><d>48</d><cT>Platform</cT><sT>23</sT></SO>
<SO><y>304</y><x>2347</x><d>49</d><cT>Platform</cT><sT>21</sT></SO>
<SO><y>304</y><x>2547</x><d>50</d><cT>Platform</cT><sT>22</sT></SO>
<SO><y>168</y><x>544</x><d>51</d><cT>Platform</cT><sT>22</sT></SO>
<SO><y>168</y><x>728</x><d>52</d><cT>Platform</cT><sT>21</sT></SO>
<SO><addProps><switchCode>3</switchCode></addProps><y>296</y><x>1010</x><d>53</d><cT>Switch</cT><sT>1</sT></SO>
<SO><addProps><switchCode>4</switchCode></addProps><y>296</y><x>1594</x><d>54</d><cT>Switch</cT><sT>0</sT></SO>
<SO><addProps><switchCode>10</switchCode></addProps><y>304</y><x>2074</x><d>55</d><cT>Switch</cT><sT>1</sT></SO>
<SO><y>304</y><x>1878</x><d>56</d><cT>Platform</cT><sT>22</sT></SO>
<SO><y>304</y><x>1947</x><d>57</d><cT>Platform</cT><sT>21</sT></SO>
<levelProperties><bkgrdA>4</bkgrdA><playerStartY>20</playerStartY><playerStartX>20</playerStartX><ScrollLockY>true</ScrollLockY><ScrollLockX>false</ScrollLockX></levelProperties>