<SO><y>135</y><x>1093</x><d>0</d><cT>Hazard</cT><sT>3</sT></SO>
<SO><addProps><maxVel>3</maxVel><tRange>-250</tRange></addProps><y>313</y><x>452</x><d>1</d><cT>YMovingPlatform</cT><sT>0</sT></SO>
<SO><addProps><maxVel>2</maxVel><rRange>500</rRange></addProps><y>312</y><x>-19</x><d>2</d><cT>XMovingPlatform</cT><sT>0</sT></SO>
<SO><y>62</y><x>795</x><d>3</d><cT>Platform</cT><sT>43</sT></SO>
<SO><addProps><maxVel>2</maxVel><rRange>425</rRange></addProps><y>62</y><x>432</x><d>4</d><cT>XMovingPlatform</cT><sT>0</sT></SO>
<SO><addProps><facingDir>left</facingDir></addProps><y>348</y><x>159</x><d>5</d><cT>Enemy</cT><sT>14</sT></SO>
<SO><addProps><facingDir>left</facingDir></addProps><y>157</y><x>742</x><d>6</d><cT>Enemy</cT><sT>17</sT></SO>
<SO><y>156</y><x>742</x><d>7</d><cT>Platform</cT><sT>8</sT></SO>
<SO><addProps><facingDir>left</facingDir></addProps><y>77</y><x>846</x><d>8</d><cT>Enemy</cT><sT>13</sT></SO>
<SO><y>328</y><x>853</x><d>9</d><cT>Platform</cT><sT>43</sT></SO>
<SO><y>328</y><x>937</x><d>10</d><cT>Platform</cT><sT>43</sT></SO>
<SO><y>328</y><x>1021</x><d>11</d><cT>Platform</cT><sT>43</sT></SO>
<SO><y>328</y><x>1105</x><d>12</d><cT>Platform</cT><sT>43</sT></SO>
<SO><y>328</y><x>1189</x><d>13</d><cT>Platform</cT><sT>43</sT></SO>
<SO><y>200</y><x>1270</x><d>14</d><cT>Wall</cT><sT>0</sT></SO>
<SO><y>310</y><x>1270</x><d>15</d><cT>Hazard</cT><sT>3</sT></SO>
<SO><y>292</y><x>1270</x><d>16</d><cT>Hazard</cT><sT>3</sT></SO>
<SO><y>274</y><x>1270</x><d>17</d><cT>Hazard</cT><sT>3</sT></SO>
<SO><y>256</y><x>1270</x><d>18</d><cT>Hazard</cT><sT>3</sT></SO>
<SO><y>238</y><x>1270</x><d>19</d><cT>Hazard</cT><sT>3</sT></SO>
<SO><y>220</y><x>1270</x><d>20</d><cT>Hazard</cT><sT>3</sT></SO>
<SO><addProps><facingDir>right</facingDir></addProps><y>77</y><x>776</x><d>21</d><cT>Enemy</cT><sT>13</sT></SO>
<SO><y>247</y><x>1240</x><d>22</d><cT>Goal</cT><sT>1</sT></SO>
<SO><y>129</y><x>1077</x><d>23</d><cT>Platform</cT><sT>8</sT></SO>
<SO><y>129</y><x>1065</x><d>24</d><cT>Ornament</cT><sT>5</sT></SO>
<SO><addProps><maxVel>3</maxVel><tRange>-200</tRange></addProps><y>328</y><x>1052</x><d>25</d><cT>YMovingPlatform</cT><sT>0</sT></SO>
<levelProperties><bkgrdA>4</bkgrdA><playerStartY>310</playerStartY><playerStartX>9</playerStartX><ScrollLockY>false</ScrollLockY><ScrollLockX>false</ScrollLockX></levelProperties>
