<SO><y>197</y><x>706</x><d>0</d><cT>Wall</cT><sT>0</sT></SO>
<SO><y>53</y><x>895</x><d>1</d><cT>Wall</cT><sT>0</sT></SO>
<SO><y>69</y><x>706</x><d>2</d><cT>Wall</cT><sT>0</sT></SO>
<SO><y>201</y><x>706</x><d>3</d><cT>Platform</cT><sT>17</sT></SO>
<SO><y>113</y><x>826</x><d>4</d><cT>Obstacle</cT><sT>3</sT></SO>
<SO><y>137</y><x>762</x><d>5</d><cT>Obstacle</cT><sT>2</sT></SO>
<SO><y>137</y><x>795</x><d>6</d><cT>Trap</cT><sT>0</sT></SO>
<SO><y>113</y><x>862</x><d>7</d><cT>Trap</cT><sT>1</sT></SO>
<SO><y>57</y><x>903</x><d>8</d><cT>Platform</cT><sT>19</sT></SO>
<SO><y>281</y><x>1</x><d>9</d><cT>Obstacle</cT><sT>2</sT></SO>
<SO><y>217</y><x>65</x><d>10</d><cT>Obstacle</cT><sT>2</sT></SO>
<SO><y>153</y><x>129</x><d>11</d><cT>Obstacle</cT><sT>2</sT></SO>
<SO><y>89</y><x>193</x><d>12</d><cT>Obstacle</cT><sT>2</sT></SO>
<SO><y>25</y><x>257</x><d>13</d><cT>Obstacle</cT><sT>2</sT></SO>
<SO><y>-39</y><x>321</x><d>14</d><cT>Obstacle</cT><sT>2</sT></SO>
<SO><y>25</y><x>321</x><d>15</d><cT>Obstacle</cT><sT>2</sT></SO>
<SO><y>89</y><x>321</x><d>16</d><cT>Obstacle</cT><sT>2</sT></SO>
<SO><y>153</y><x>321</x><d>17</d><cT>Obstacle</cT><sT>2</sT></SO>
<SO><y>217</y><x>321</x><d>18</d><cT>Obstacle</cT><sT>2</sT></SO>
<SO><y>281</y><x>321</x><d>19</d><cT>Obstacle</cT><sT>2</sT></SO>
<SO><y>89</y><x>257</x><d>20</d><cT>Obstacle</cT><sT>2</sT></SO>
<SO><y>153</y><x>257</x><d>21</d><cT>Obstacle</cT><sT>2</sT></SO>
<SO><y>281</y><x>257</x><d>22</d><cT>Obstacle</cT><sT>2</sT></SO>
<SO><y>217</y><x>257</x><d>23</d><cT>Obstacle</cT><sT>2</sT></SO>
<SO><y>153</y><x>193</x><d>24</d><cT>Obstacle</cT><sT>2</sT></SO>
<SO><y>281</y><x>65</x><d>25</d><cT>Obstacle</cT><sT>2</sT></SO>
<SO><y>281</y><x>193</x><d>26</d><cT>Obstacle</cT><sT>2</sT></SO>
<SO><y>217</y><x>193</x><d>27</d><cT>Obstacle</cT><sT>2</sT></SO>
<SO><y>281</y><x>129</x><d>28</d><cT>Obstacle</cT><sT>2</sT></SO>
<SO><y>217</y><x>129</x><d>29</d><cT>Obstacle</cT><sT>2</sT></SO>
<SO><y>25</y><x>385</x><d>30</d><cT>Obstacle</cT><sT>2</sT></SO>
<SO><y>89</y><x>385</x><d>31</d><cT>Obstacle</cT><sT>2</sT></SO>
<SO><y>89</y><x>449</x><d>32</d><cT>Obstacle</cT><sT>2</sT></SO>
<SO><y>153</y><x>513</x><d>33</d><cT>Obstacle</cT><sT>2</sT></SO>
<SO><y>217</y><x>577</x><d>34</d><cT>Obstacle</cT><sT>2</sT></SO>
<SO><y>281</y><x>641</x><d>35</d><cT>Obstacle</cT><sT>2</sT></SO>
<SO><y>153</y><x>385</x><d>36</d><cT>Obstacle</cT><sT>2</sT></SO>
<SO><y>153</y><x>449</x><d>37</d><cT>Obstacle</cT><sT>2</sT></SO>
<SO><y>281</y><x>385</x><d>38</d><cT>Obstacle</cT><sT>2</sT></SO>
<SO><y>217</y><x>385</x><d>39</d><cT>Obstacle</cT><sT>2</sT></SO>
<SO><y>217</y><x>449</x><d>40</d><cT>Obstacle</cT><sT>2</sT></SO>
<SO><y>217</y><x>513</x><d>41</d><cT>Obstacle</cT><sT>2</sT></SO>
<SO><y>281</y><x>449</x><d>42</d><cT>Obstacle</cT><sT>2</sT></SO>
<SO><y>281</y><x>513</x><d>43</d><cT>Obstacle</cT><sT>2</sT></SO>
<SO><y>281</y><x>577</x><d>44</d><cT>Obstacle</cT><sT>2</sT></SO>
<SO><addProps><facingDir>left</facingDir></addProps><y>-39</y><x>316</x><d>45</d><cT>Enemy</cT><sT>2</sT></SO>
<SO><addProps><facingDir>right</facingDir></addProps><y>-39</y><x>390</x><d>46</d><cT>Enemy</cT><sT>2</sT></SO>
<SO><addProps><facingDir>left</facingDir></addProps><y>89</y><x>230</x><d>47</d><cT>Enemy</cT><sT>4</sT></SO>
<SO><addProps><facingDir>left</facingDir></addProps><y>25</y><x>294</x><d>48</d><cT>Enemy</cT><sT>4</sT></SO>
<SO><addProps><maxVelX>4</maxVelX><rRange>48</rRange><facingDir>left</facingDir></addProps><y>154</y><x>136</x><d>49</d><cT>Enemy</cT><sT>22</sT></SO>
<SO><addProps><facingDir>left</facingDir></addProps><y>217</y><x>97</x><d>50</d><cT>Enemy</cT><sT>10</sT></SO>
<SO><addProps><facingDir>left</facingDir></addProps><y>-38</y><x>348</x><d>51</d><cT>Enemy</cT><sT>40</sT></SO>
<SO><addProps><facingDir>left</facingDir></addProps><y>25</y><x>418</x><d>52</d><cT>Enemy</cT><sT>17</sT></SO>
<SO><addProps><facingDir>right</facingDir></addProps><y>89</y><x>503</x><d>53</d><cT>Enemy</cT><sT>15</sT></SO>
<SO><addProps><facingDir>left</facingDir></addProps><y>155</y><x>563</x><d>54</d><cT>Enemy</cT><sT>21</sT></SO>
<SO><addProps><shotsToFire>1</shotsToFire><facingDir>left</facingDir></addProps><y>281</y><x>619</x><d>55</d><cT>Enemy</cT><sT>12</sT></SO>
<SO><addProps><facingDir>left</facingDir><velX>-3</velX><velY>0</velY></addProps><y>122</y><x>615</x><d>56</d><cT>Enemy</cT><sT>38</sT></SO>
<SO><y>65</y><x>666</x><d>57</d><cT>Ladder</cT><sT>0</sT></SO>
<SO><y>137</y><x>666</x><d>58</d><cT>Ladder</cT><sT>0</sT></SO>
<SO><y>209</y><x>666</x><d>59</d><cT>Ladder</cT><sT>0</sT></SO>
<SO><y>65</y><x>666</x><d>60</d><cT>Platform</cT><sT>16</sT></SO>
<SO><y>263</y><x>857</x><d>61</d><cT>Platform</cT><sT>13</sT></SO>
<SO><addProps><facingDir>left</facingDir></addProps><y>265</y><x>745</x><d>62</d><cT>Enemy</cT><sT>4</sT></SO>
<SO><addProps><facingDir>left</facingDir></addProps><y>265</y><x>851</x><d>63</d><cT>Enemy</cT><sT>4</sT></SO>
<SO><addProps><facingDir>left</facingDir></addProps><y>265</y><x>904</x><d>64</d><cT>Enemy</cT><sT>4</sT></SO>
<SO><addProps><facingDir>left</facingDir></addProps><y>265</y><x>957</x><d>65</d><cT>Enemy</cT><sT>4</sT></SO>
<SO><y>57</y><x>971</x><d>66</d><cT>Platform</cT><sT>43</sT></SO>
<SO><y>57</y><x>1055</x><d>67</d><cT>Platform</cT><sT>43</sT></SO>
<SO><y>57</y><x>1139</x><d>68</d><cT>Platform</cT><sT>43</sT></SO>
<SO><y>142</y><x>1131</x><d>69</d><cT>Platform</cT><sT>42</sT></SO>
<SO><y>142</y><x>1047</x><d>70</d><cT>Platform</cT><sT>42</sT></SO>
<SO><y>142</y><x>963</x><d>71</d><cT>Platform</cT><sT>42</sT></SO>
<SO><y>142</y><x>1215</x><d>72</d><cT>Platform</cT><sT>42</sT></SO>
<SO><addProps><facingDir>left</facingDir></addProps><y>265</y><x>798</x><d>73</d><cT>Enemy</cT><sT>17</sT></SO>
<SO><y>14</y><x>1296</x><d>74</d><cT>Wall</cT><sT>0</sT></SO>
<SO><y>-130</y><x>1296</x><d>75</d><cT>Wall</cT><sT>0</sT></SO>
<SO><y>55</y><x>694</x><d>76</d><cT>Powerup</cT><sT>0</sT></SO>
<SO><y>263</y><x>1137</x><d>77</d><cT>Platform</cT><sT>13</sT></SO>
<SO><y>263</y><x>1419</x><d>78</d><cT>Platform</cT><sT>13</sT></SO>
<SO><y>263</y><x>1701</x><d>79</d><cT>Platform</cT><sT>13</sT></SO>
<SO><addProps><maxVelX>4</maxVelX><rRange>100</rRange><facingDir>left</facingDir></addProps><y>57</y><x>921</x><d>80</d><cT>Enemy</cT><sT>6</sT></SO>
<SO><addProps><maxVelX>4</maxVelX><rRange>100</rRange><facingDir>left</facingDir></addProps><y>57</y><x>1082</x><d>81</d><cT>Enemy</cT><sT>6</sT></SO>
<SO><addProps><maxVelX>4</maxVelX><rRange>100</rRange><facingDir>left</facingDir></addProps><y>142</y><x>1103</x><d>82</d><cT>Enemy</cT><sT>6</sT></SO>
<SO><addProps><facingDir>left</facingDir></addProps><y>142</y><x>986</x><d>83</d><cT>Enemy</cT><sT>4</sT></SO>
<SO><addProps><facingDir>left</facingDir><jumpingDir>-1</jumpingDir></addProps><y>263</y><x>1029</x><d>84</d><cT>Enemy</cT><sT>3</sT></SO>
<SO><addProps><facingDir>left</facingDir><jumpingDir>-1</jumpingDir></addProps><y>263</y><x>1083</x><d>85</d><cT>Enemy</cT><sT>3</sT></SO>
<SO><addProps><facingDir>left</facingDir><jumpingDir>-1</jumpingDir></addProps><y>263</y><x>1135</x><d>86</d><cT>Enemy</cT><sT>3</sT></SO>
<SO><addProps><facingDir>left</facingDir></addProps><y>265</y><x>798</x><d>87</d><cT>Enemy</cT><sT>4</sT></SO>
<SO><y>181</y><x>936</x><d>88</d><cT>Powerup</cT><sT>0</sT></SO>
<SO><y>-127</y><x>1302</x><d>89</d><cT>Hazard</cT><sT>4</sT></SO>
<SO><y>90</y><x>1225</x><d>90</d><cT>Trap</cT><sT>2</sT></SO>
<SO><y>86</y><x>1225</x><d>91</d><cT>Trap</cT><sT>5</sT></SO>
<SO><y>175</y><x>1303</x><d>92</d><cT>Trap</cT><sT>3</sT></SO>
<SO><y>230</y><x>1321</x><d>93</d><cT>Trap</cT><sT>10</sT></SO>
<SO><y>209</y><x>1480</x><d>94</d><cT>Platform</cT><sT>15</sT></SO>
<SO><y>209</y><x>1640</x><d>95</d><cT>Platform</cT><sT>14</sT></SO>
<SO><y>209</y><x>1480</x><d>96</d><cT>Platform</cT><sT>12</sT></SO>
<SO><y>137</y><x>1560</x><d>97</d><cT>Ladder</cT><sT>0</sT></SO>
<SO><y>65</y><x>1560</x><d>98</d><cT>Ladder</cT><sT>0</sT></SO>
<SO><y>65</y><x>1510</x><d>99</d><cT>Obstacle</cT><sT>4</sT></SO>
<SO><y>215</y><x>1513</x><d>100</d><cT>Trap</cT><sT>4</sT></SO>
<SO><y>215</y><x>1607</x><d>101</d><cT>Trap</cT><sT>4</sT></SO>
<SO><y>209</y><x>1560</x><d>102</d><cT>Trap</cT><sT>1</sT></SO>
<SO><addProps><facingDir>left</facingDir></addProps><y>209</y><x>1560</x><d>103</d><cT>Enemy</cT><sT>4</sT></SO>
<SO><y>109</y><x>1664</x><d>104</d><cT>Ornament</cT><sT>20</sT></SO>
<SO><y>55</y><x>1640</x><d>105</d><cT>Obstacle</cT><sT>5</sT></SO>
<SO><y>53</y><x>1695</x><d>106</d><cT>Platform</cT><sT>41</sT></SO>
<SO><addProps><facingDir>left</facingDir></addProps><y>263</y><x>1233</x><d>107</d><cT>Enemy</cT><sT>8</sT></SO>
<SO><y>263</y><x>1673</x><d>108</d><cT>Hazard</cT><sT>0</sT></SO>
<SO><y>263</y><x>1691</x><d>109</d><cT>Hazard</cT><sT>0</sT></SO>
<SO><y>263</y><x>1709</x><d>110</d><cT>Hazard</cT><sT>0</sT></SO>
<SO><y>9</y><x>1721</x><d>111</d><cT>Platform</cT><sT>41</sT></SO>
<SO><addProps><facingDir>left</facingDir></addProps><y>233</y><x>1692</x><d>112</d><cT>Enemy</cT><sT>23</sT></SO>
<SO><y>263</y><x>1981</x><d>113</d><cT>Platform</cT><sT>13</sT></SO>
<SO><y>263</y><x>1727</x><d>114</d><cT>Hazard</cT><sT>0</sT></SO>
<SO><y>263</y><x>1745</x><d>115</d><cT>Hazard</cT><sT>0</sT></SO>
<SO><addProps><facingDir>left</facingDir></addProps><y>66</y><x>1640</x><d>116</d><cT>Enemy</cT><sT>2</sT></SO>
<SO><y>263</y><x>1785</x><d>117</d><cT>Trap</cT><sT>0</sT></SO>
<SO><y>172</y><x>1775</x><d>118</d><cT>Trap</cT><sT>6</sT></SO>
<SO><y>263</y><x>1856</x><d>119</d><cT>Trap</cT><sT>1</sT></SO>
<SO><y>265</y><x>1833</x><d>120</d><cT>Trap</cT><sT>2</sT></SO>
<SO><y>263</y><x>1895</x><d>121</d><cT>Trap</cT><sT>7</sT></SO>
<SO><y>230</y><x>1784</x><d>122</d><cT>Trap</cT><sT>10</sT></SO>
<SO><y>263</y><x>1852</x><d>123</d><cT>Trap</cT><sT>0</sT></SO>
<SO><y>172</y><x>1842</x><d>124</d><cT>Trap</cT><sT>6</sT></SO>
<SO><y>263</y><x>1923</x><d>125</d><cT>Trap</cT><sT>1</sT></SO>
<SO><y>265</y><x>1900</x><d>126</d><cT>Trap</cT><sT>2</sT></SO>
<SO><y>263</y><x>1962</x><d>127</d><cT>Trap</cT><sT>7</sT></SO>
<SO><y>230</y><x>1851</x><d>128</d><cT>Trap</cT><sT>10</sT></SO>
<SO><y>263</y><x>1816</x><d>129</d><cT>Trap</cT><sT>0</sT></SO>
<SO><y>172</y><x>1806</x><d>130</d><cT>Trap</cT><sT>6</sT></SO>
<SO><y>263</y><x>1887</x><d>131</d><cT>Trap</cT><sT>1</sT></SO>
<SO><y>265</y><x>1864</x><d>132</d><cT>Trap</cT><sT>2</sT></SO>
<SO><y>263</y><x>1926</x><d>133</d><cT>Trap</cT><sT>7</sT></SO>
<SO><y>230</y><x>1815</x><d>134</d><cT>Trap</cT><sT>10</sT></SO>
<SO><y>263</y><x>1780</x><d>135</d><cT>Trap</cT><sT>0</sT></SO>
<SO><y>172</y><x>1770</x><d>136</d><cT>Trap</cT><sT>6</sT></SO>
<SO><y>263</y><x>1851</x><d>137</d><cT>Trap</cT><sT>1</sT></SO>
<SO><y>265</y><x>1828</x><d>138</d><cT>Trap</cT><sT>2</sT></SO>
<SO><y>263</y><x>1890</x><d>139</d><cT>Trap</cT><sT>7</sT></SO>
<SO><y>230</y><x>1779</x><d>140</d><cT>Trap</cT><sT>10</sT></SO>
<SO><y>263</y><x>1785</x><d>141</d><cT>Trap</cT><sT>0</sT></SO>
<SO><y>172</y><x>1775</x><d>142</d><cT>Trap</cT><sT>6</sT></SO>
<SO><y>263</y><x>1856</x><d>143</d><cT>Trap</cT><sT>1</sT></SO>
<SO><y>265</y><x>1833</x><d>144</d><cT>Trap</cT><sT>2</sT></SO>
<SO><y>263</y><x>1895</x><d>145</d><cT>Trap</cT><sT>7</sT></SO>
<SO><y>230</y><x>1784</x><d>146</d><cT>Trap</cT><sT>10</sT></SO>
<SO><y>263</y><x>1852</x><d>147</d><cT>Trap</cT><sT>0</sT></SO>
<SO><y>172</y><x>1842</x><d>148</d><cT>Trap</cT><sT>6</sT></SO>
<SO><y>263</y><x>1923</x><d>149</d><cT>Trap</cT><sT>1</sT></SO>
<SO><y>265</y><x>1900</x><d>150</d><cT>Trap</cT><sT>2</sT></SO>
<SO><y>263</y><x>1962</x><d>151</d><cT>Trap</cT><sT>7</sT></SO>
<SO><y>230</y><x>1851</x><d>152</d><cT>Trap</cT><sT>10</sT></SO>
<SO><y>263</y><x>1816</x><d>153</d><cT>Trap</cT><sT>0</sT></SO>
<SO><y>172</y><x>1806</x><d>154</d><cT>Trap</cT><sT>6</sT></SO>
<SO><y>263</y><x>1887</x><d>155</d><cT>Trap</cT><sT>1</sT></SO>
<SO><y>265</y><x>1864</x><d>156</d><cT>Trap</cT><sT>2</sT></SO>
<SO><y>263</y><x>1926</x><d>157</d><cT>Trap</cT><sT>7</sT></SO>
<SO><y>230</y><x>1815</x><d>158</d><cT>Trap</cT><sT>10</sT></SO>
<SO><y>263</y><x>1780</x><d>159</d><cT>Trap</cT><sT>0</sT></SO>
<SO><y>172</y><x>1770</x><d>160</d><cT>Trap</cT><sT>6</sT></SO>
<SO><y>263</y><x>1851</x><d>161</d><cT>Trap</cT><sT>1</sT></SO>
<SO><y>265</y><x>1828</x><d>162</d><cT>Trap</cT><sT>2</sT></SO>
<SO><y>263</y><x>1890</x><d>163</d><cT>Trap</cT><sT>7</sT></SO>
<SO><y>230</y><x>1779</x><d>164</d><cT>Trap</cT><sT>10</sT></SO>
<SO><y>263</y><x>2263</x><d>165</d><cT>Platform</cT><sT>13</sT></SO>
<SO><y>263</y><x>2545</x><d>166</d><cT>Platform</cT><sT>13</sT></SO>
<SO><y>263</y><x>2827</x><d>167</d><cT>Platform</cT><sT>13</sT></SO>
<SO><y>263</y><x>2052</x><d>168</d><cT>Goal</cT><sT>1</sT></SO>
<SO><y>-6</y><x>1779</x><d>169</d><cT>Trap</cT><sT>2</sT></SO>
<SO><y>-30</y><x>1779</x><d>170</d><cT>Platform</cT><sT>6</sT></SO>
<SO><y>-30</y><x>1779</x><d>171</d><cT>Platform</cT><sT>5</sT></SO>
<SO><y>34</y><x>1769</x><d>172</d><cT>Hazard</cT><sT>0</sT></SO>
<SO><y>34</y><x>1769</x><d>173</d><cT>Hazard</cT><sT>1</sT></SO>
<SO><y>25</y><x>1768</x><d>174</d><cT>Hazard</cT><sT>3</sT></SO>
<SO><y>25</y><x>1768</x><d>175</d><cT>Hazard</cT><sT>2</sT></SO>
<SO><y>95</y><x>937</x><d>176</d><cT>Hazard</cT><sT>0</sT></SO>
<SO><y>86</y><x>936</x><d>177</d><cT>Hazard</cT><sT>3</sT></SO>
<SO><y>86</y><x>936</x><d>178</d><cT>Hazard</cT><sT>2</sT></SO>
<levelProperties><bkgrdA>8</bkgrdA><playerStartY>200</playerStartY><playerStartX>33</playerStartX><ScrollLockY>false</ScrollLockY><ScrollLockX>false</ScrollLockX></levelProperties>
