<SO><y>306</y><x>1</x><d>0</d><cT>Platform</cT><sT>9</sT></SO>
<SO><y>306</y><x>197</x><d>1</d><cT>Platform</cT><sT>9</sT></SO>
<SO><y>306</y><x>785</x><d>2</d><cT>Platform</cT><sT>10</sT></SO>
<SO><y>268</y><x>579</x><d>3</d><cT>Platform</cT><sT>9</sT></SO>
<SO><y>268</y><x>775</x><d>4</d><cT>Platform</cT><sT>10</sT></SO>
<SO><y>268</y><x>580</x><d>5</d><cT>Platform</cT><sT>11</sT></SO>
<SO><y>247</y><x>599</x><d>6</d><cT>Platform</cT><sT>43</sT></SO>
<SO><y>247</y><x>683</x><d>7</d><cT>Platform</cT><sT>43</sT></SO>
<SO><y>119</y><x>764</x><d>8</d><cT>Wall</cT><sT>0</sT></SO>
<SO><y>247</y><x>606</x><d>9</d><cT>Trap</cT><sT>0</sT></SO>
<SO><y>306</y><x>589</x><d>10</d><cT>Platform</cT><sT>9</sT></SO>
<SO><y>306</y><x>393</x><d>11</d><cT>Platform</cT><sT>9</sT></SO>
<SO><y>156</y><x>765</x><d>12</d><cT>Hazard</cT><sT>3</sT></SO>
<SO><y>175</y><x>765</x><d>13</d><cT>Hazard</cT><sT>3</sT></SO>
<SO><y>192</y><x>765</x><d>14</d><cT>Hazard</cT><sT>3</sT></SO>
<SO><y>211</y><x>765</x><d>15</d><cT>Hazard</cT><sT>3</sT></SO>
<SO><y>139</y><x>765</x><d>16</d><cT>Hazard</cT><sT>3</sT></SO>
<SO><y>229</y><x>765</x><d>17</d><cT>Hazard</cT><sT>3</sT></SO>
<SO><addProps><facingDir>left</facingDir></addProps><y>247</y><x>743</x><d>18</d><cT>Enemy</cT><sT>8</sT></SO>
<SO><addProps><facingDir>left</facingDir></addProps><y>215</y><x>168</x><d>19</d><cT>Enemy</cT><sT>19</sT></SO>
<SO><addProps><facingDir>left</facingDir></addProps><y>215</y><x>215</x><d>20</d><cT>Enemy</cT><sT>19</sT></SO>
<SO><addProps><facingDir>left</facingDir></addProps><y>215</y><x>120</x><d>21</d><cT>Enemy</cT><sT>19</sT></SO>
<SO><addProps><facingDir>left</facingDir></addProps><y>307</y><x>543</x><d>22</d><cT>Enemy</cT><sT>4</sT></SO>
<SO><addProps><facingDir>left</facingDir></addProps><y>305</y><x>717</x><d>23</d><cT>Enemy</cT><sT>41</sT></SO>
<SO><addProps><maxVel>3</maxVel><tRange>-108</tRange></addProps><y>225</y><x>665</x><d>24</d><cT>YMovingPlatform</cT><sT>3</sT></SO>
<SO><y>113</y><x>735</x><d>25</d><cT>Platform</cT><sT>20</sT></SO>
<SO><y>41</y><x>752</x><d>26</d><cT>Ladder</cT><sT>1</sT></SO>
<SO><y>-31</y><x>752</x><d>27</d><cT>Ladder</cT><sT>1</sT></SO>
<SO><y>-103</y><x>752</x><d>28</d><cT>Ladder</cT><sT>1</sT></SO>
<SO><y>-175</y><x>752</x><d>29</d><cT>Ladder</cT><sT>1</sT></SO>
<SO><y>113</y><x>799</x><d>30</d><cT>Platform</cT><sT>22</sT></SO>
<SO><y>114</y><x>728</x><d>31</d><cT>Platform</cT><sT>21</sT></SO>
<SO><addProps><maxVelX>4</maxVelX><rRange>200</rRange><facingDir>right</facingDir></addProps><y>-22</y><x>696</x><d>32</d><cT>Enemy</cT><sT>7</sT></SO>
<SO><addProps><facingDir>left</facingDir></addProps><y>-95</y><x>771</x><d>33</d><cT>Enemy</cT><sT>24</sT></SO>
<SO><addProps><facingDir>right</facingDir></addProps><y>-95</y><x>771</x><d>34</d><cT>Enemy</cT><sT>24</sT></SO>
<SO><y>13</y><x>772</x><d>35</d><cT>Powerup</cT><sT>0</sT></SO>
<SO><addProps><facingDir>left</facingDir></addProps><y>57</y><x>769</x><d>36</d><cT>Enemy</cT><sT>9</sT></SO>
<SO><y>307</y><x>714</x><d>37</d><cT>ShooterObstacle</cT><sT>18</sT></SO>
<SO><addProps><maxVel>3</maxVel><rRange>110</rRange></addProps><y>112</y><x>645</x><d>38</d><cT>XMovingPlatform</cT><sT>3</sT></SO>
<SO><addProps><facingDir>left</facingDir></addProps><y>307</y><x>490</x><d>39</d><cT>Enemy</cT><sT>4</sT></SO>
<SO><addProps><facingDir>left</facingDir></addProps><y>307</y><x>437</x><d>40</d><cT>Enemy</cT><sT>4</sT></SO>
<SO><addProps><facingDir>left</facingDir></addProps><y>307</y><x>384</x><d>41</d><cT>Enemy</cT><sT>4</sT></SO>
<SO><addProps><facingDir>left</facingDir></addProps><y>307</y><x>331</x><d>42</d><cT>Enemy</cT><sT>4</sT></SO>
<SO><addProps><facingDir>left</facingDir></addProps><y>307</y><x>278</x><d>43</d><cT>Enemy</cT><sT>4</sT></SO>
<SO><addProps><facingDir>left</facingDir><jumpingDir>-1</jumpingDir></addProps><y>112</y><x>790</x><d>44</d><cT>Enemy</cT><sT>3</sT></SO>
<SO><addProps><facingDir>left</facingDir><jumpingDir>-1</jumpingDir></addProps><y>307</y><x>96</x><d>45</d><cT>Enemy</cT><sT>5</sT></SO>
<SO><y>-175</y><x>597</x><d>46</d><cT>Platform</cT><sT>29</sT></SO>
<SO><y>-175</y><x>405</x><d>47</d><cT>Platform</cT><sT>29</sT></SO>
<SO><y>-175</y><x>213</x><d>48</d><cT>Platform</cT><sT>29</sT></SO>
<SO><y>-175</y><x>213</x><d>49</d><cT>Platform</cT><sT>31</sT></SO>
<SO><y>-175</y><x>789</x><d>50</d><cT>Platform</cT><sT>30</sT></SO>
<SO><addProps><facingDir>left</facingDir></addProps><y>-160</y><x>469</x><d>51</d><cT>Enemy</cT><sT>18</sT></SO>
<SO><addProps><facingDir>right</facingDir></addProps><y>-175</y><x>702</x><d>52</d><cT>Enemy</cT><sT>0</sT></SO>
<SO><addProps><facingDir>right</facingDir></addProps><y>-175</y><x>342</x><d>53</d><cT>Enemy</cT><sT>0</sT></SO>
<SO><addProps><facingDir>right</facingDir></addProps><y>-175</y><x>372</x><d>54</d><cT>Enemy</cT><sT>0</sT></SO>
<SO><addProps><facingDir>right</facingDir></addProps><y>-175</y><x>402</x><d>55</d><cT>Enemy</cT><sT>0</sT></SO>
<SO><addProps><facingDir>right</facingDir></addProps><y>-175</y><x>432</x><d>56</d><cT>Enemy</cT><sT>0</sT></SO>
<SO><addProps><facingDir>right</facingDir></addProps><y>-175</y><x>462</x><d>57</d><cT>Enemy</cT><sT>0</sT></SO>
<SO><addProps><facingDir>right</facingDir></addProps><y>-175</y><x>492</x><d>58</d><cT>Enemy</cT><sT>0</sT></SO>
<SO><addProps><facingDir>right</facingDir></addProps><y>-175</y><x>522</x><d>59</d><cT>Enemy</cT><sT>0</sT></SO>
<SO><addProps><facingDir>right</facingDir></addProps><y>-175</y><x>552</x><d>60</d><cT>Enemy</cT><sT>0</sT></SO>
<SO><addProps><facingDir>right</facingDir></addProps><y>-175</y><x>582</x><d>61</d><cT>Enemy</cT><sT>0</sT></SO>
<SO><addProps><facingDir>right</facingDir></addProps><y>-175</y><x>612</x><d>62</d><cT>Enemy</cT><sT>0</sT></SO>
<SO><addProps><facingDir>right</facingDir></addProps><y>-175</y><x>642</x><d>63</d><cT>Enemy</cT><sT>0</sT></SO>
<SO><addProps><facingDir>right</facingDir></addProps><y>-175</y><x>672</x><d>64</d><cT>Enemy</cT><sT>0</sT></SO>
<SO><addProps><facingDir>right</facingDir></addProps><y>-175</y><x>294</x><d>65</d><cT>Enemy</cT><sT>21</sT></SO>
<SO><y>-247</y><x>201</x><d>66</d><cT>Ladder</cT><sT>0</sT></SO>
<SO><y>-319</y><x>201</x><d>67</d><cT>Ladder</cT><sT>0</sT></SO>
<SO><y>-391</y><x>201</x><d>68</d><cT>Ladder</cT><sT>0</sT></SO>
<SO><y>-463</y><x>201</x><d>69</d><cT>Ladder</cT><sT>0</sT></SO>
<SO><y>-535</y><x>201</x><d>70</d><cT>Ladder</cT><sT>0</sT></SO>
<SO><y>-607</y><x>201</x><d>71</d><cT>Ladder</cT><sT>0</sT></SO>
<SO><y>-679</y><x>201</x><d>72</d><cT>Ladder</cT><sT>0</sT></SO>
<SO><y>-391</y><x>252</x><d>73</d><cT>Ornament</cT><sT>17</sT></SO>
<SO><y>-472</y><x>252</x><d>74</d><cT>Ornament</cT><sT>17</sT></SO>
<SO><y>-566</y><x>252</x><d>75</d><cT>Ornament</cT><sT>17</sT></SO>
<SO><y>-391</y><x>123</x><d>76</d><cT>Platform</cT><sT>16</sT></SO>
<SO><y>-472</y><x>123</x><d>77</d><cT>Ornament</cT><sT>17</sT></SO>
<SO><y>-566</y><x>123</x><d>78</d><cT>Ornament</cT><sT>17</sT></SO>
<SO><addProps><facingDir>right</facingDir></addProps><y>-472</y><x>160</x><d>79</d><cT>Enemy</cT><sT>28</sT></SO>
<SO><addProps><facingDir>left</facingDir></addProps><y>-391</y><x>282</x><d>80</d><cT>Enemy</cT><sT>8</sT></SO>
<SO><addProps><facingDir>left</facingDir></addProps><y>-566</y><x>283</x><d>81</d><cT>Enemy</cT><sT>8</sT></SO>
<SO><addProps><facingDir>left</facingDir></addProps><y>-472</y><x>283</x><d>82</d><cT>Enemy</cT><sT>16</sT></SO>
<SO><y>-401</y><x>160</x><d>83</d><cT>Powerup</cT><sT>0</sT></SO>
<SO><addProps><facingDir>left</facingDir></addProps><y>-391</y><x>158</x><d>84</d><cT>Enemy</cT><sT>4</sT></SO>
<SO><y>-679</y><x>201</x><d>85</d><cT>Platform</cT><sT>23</sT></SO>
<SO><y>-679</y><x>393</x><d>86</d><cT>Platform</cT><sT>23</sT></SO>
<SO><y>-679</y><x>585</x><d>87</d><cT>Platform</cT><sT>23</sT></SO>
<SO><y>-679</y><x>777</x><d>88</d><cT>Platform</cT><sT>22</sT></SO>
<SO><y>-679</y><x>193</x><d>89</d><cT>Platform</cT><sT>21</sT></SO>
<SO><addProps><shotsToFire>5</shotsToFire><facingDir>left</facingDir></addProps><y>-679</y><x>645</x><d>90</d><cT>Enemy</cT><sT>12</sT></SO>
<SO><addProps><facingDir>left</facingDir></addProps><y>-717</y><x>423</x><d>91</d><cT>Enemy</cT><sT>9</sT></SO>
<SO><addProps><facingDir>left</facingDir></addProps><y>-717</y><x>463</x><d>92</d><cT>Enemy</cT><sT>9</sT></SO>
<SO><addProps><facingDir>left</facingDir></addProps><y>-717</y><x>503</x><d>93</d><cT>Enemy</cT><sT>9</sT></SO>
<SO><addProps><facingDir>left</facingDir></addProps><y>-717</y><x>543</x><d>94</d><cT>Enemy</cT><sT>9</sT></SO>
<SO><addProps><facingDir>left</facingDir></addProps><y>-717</y><x>583</x><d>95</d><cT>Enemy</cT><sT>9</sT></SO>
<SO><addProps><facingDir>left</facingDir></addProps><y>-736</y><x>383</x><d>96</d><cT>Enemy</cT><sT>9</sT></SO>
<SO><addProps><facingDir>left</facingDir></addProps><y>-736</y><x>423</x><d>97</d><cT>Enemy</cT><sT>9</sT></SO>
<SO><addProps><facingDir>left</facingDir></addProps><y>-736</y><x>463</x><d>98</d><cT>Enemy</cT><sT>9</sT></SO>
<SO><addProps><facingDir>left</facingDir></addProps><y>-736</y><x>503</x><d>99</d><cT>Enemy</cT><sT>9</sT></SO>
<SO><addProps><facingDir>left</facingDir></addProps><y>-736</y><x>543</x><d>100</d><cT>Enemy</cT><sT>9</sT></SO>
<SO><addProps><facingDir>left</facingDir></addProps><y>-755</y><x>433</x><d>101</d><cT>Enemy</cT><sT>9</sT></SO>
<SO><addProps><facingDir>left</facingDir></addProps><y>-755</y><x>473</x><d>102</d><cT>Enemy</cT><sT>9</sT></SO>
<SO><addProps><facingDir>left</facingDir></addProps><y>-755</y><x>513</x><d>103</d><cT>Enemy</cT><sT>9</sT></SO>
<SO><addProps><facingDir>left</facingDir></addProps><y>-755</y><x>553</x><d>104</d><cT>Enemy</cT><sT>9</sT></SO>
<SO><addProps><facingDir>left</facingDir></addProps><y>-755</y><x>593</x><d>105</d><cT>Enemy</cT><sT>9</sT></SO>
<SO><addProps><facingDir>left</facingDir></addProps><y>-774</y><x>393</x><d>106</d><cT>Enemy</cT><sT>9</sT></SO>
<SO><addProps><facingDir>left</facingDir></addProps><y>-774</y><x>433</x><d>107</d><cT>Enemy</cT><sT>9</sT></SO>
<SO><addProps><facingDir>left</facingDir></addProps><y>-774</y><x>473</x><d>108</d><cT>Enemy</cT><sT>9</sT></SO>
<SO><addProps><facingDir>left</facingDir></addProps><y>-774</y><x>513</x><d>109</d><cT>Enemy</cT><sT>9</sT></SO>
<SO><addProps><facingDir>left</facingDir></addProps><y>-774</y><x>553</x><d>110</d><cT>Enemy</cT><sT>9</sT></SO>
<SO><addProps><facingDir>left</facingDir></addProps><y>-793</y><x>423</x><d>111</d><cT>Enemy</cT><sT>9</sT></SO>
<SO><addProps><facingDir>left</facingDir></addProps><y>-793</y><x>463</x><d>112</d><cT>Enemy</cT><sT>9</sT></SO>
<SO><addProps><facingDir>left</facingDir></addProps><y>-793</y><x>503</x><d>113</d><cT>Enemy</cT><sT>9</sT></SO>
<SO><addProps><facingDir>left</facingDir></addProps><y>-793</y><x>543</x><d>114</d><cT>Enemy</cT><sT>9</sT></SO>
<SO><addProps><facingDir>left</facingDir></addProps><y>-793</y><x>583</x><d>115</d><cT>Enemy</cT><sT>9</sT></SO>
<SO><y>-751</y><x>743</x><d>116</d><cT>Ladder</cT><sT>1</sT></SO>
<SO><y>-823</y><x>743</x><d>117</d><cT>Ladder</cT><sT>1</sT></SO>
<SO><y>-895</y><x>743</x><d>118</d><cT>Ladder</cT><sT>1</sT></SO>
<SO><y>-967</y><x>743</x><d>119</d><cT>Ladder</cT><sT>1</sT></SO>
<SO><addProps><facingDir>left</facingDir></addProps><y>-895</y><x>835</x><d>120</d><cT>Enemy</cT><sT>2</sT></SO>
<SO><y>-901</y><x>777</x><d>121</d><cT>Ornament</cT><sT>16</sT></SO>
<SO><addProps><facingDir>left</facingDir></addProps><y>-780</y><x>830</x><d>122</d><cT>Enemy</cT><sT>17</sT></SO>
<SO><y>-780</y><x>797</x><d>123</d><cT>Ornament</cT><sT>17</sT></SO>
<SO><y>-679</y><x>797</x><d>124</d><cT>Platform</cT><sT>16</sT></SO>
<SO><y>-689</y><x>830</x><d>125</d><cT>Powerup</cT><sT>0</sT></SO>
<SO><y>-1039</y><x>743</x><d>126</d><cT>Ladder</cT><sT>1</sT></SO>
<SO><y>-1039</y><x>577</x><d>127</d><cT>Platform</cT><sT>17</sT></SO>
<SO><y>-1039</y><x>377</x><d>128</d><cT>Platform</cT><sT>17</sT></SO>
<SO><y>-1039</y><x>177</x><d>129</d><cT>Platform</cT><sT>17</sT></SO>
<SO><y>-1040</y><x>191</x><d>130</d><cT>Hazard</cT><sT>4</sT></SO>
<SO><y>-1040</y><x>283</x><d>131</d><cT>Hazard</cT><sT>4</sT></SO>
<SO><y>-1111</y><x>205</x><d>132</d><cT>Ladder</cT><sT>1</sT></SO>
<SO><y>-1399</y><x>205</x><d>133</d><cT>Ladder</cT><sT>1</sT></SO>
<SO><y>-1327</y><x>205</x><d>134</d><cT>Ladder</cT><sT>1</sT></SO>
<SO><y>-1255</y><x>205</x><d>135</d><cT>Ladder</cT><sT>1</sT></SO>
<SO><y>-1183</y><x>205</x><d>136</d><cT>Ladder</cT><sT>1</sT></SO>
<SO><addProps><maxVelX>2</maxVelX><rRange>400</rRange><facingDir>left</facingDir></addProps><y>-1126</y><x>16</x><d>137</d><cT>Enemy</cT><sT>22</sT></SO>
<SO><y>-1399</y><x>205</x><d>138</d><cT>Platform</cT><sT>29</sT></SO>
<SO><y>-1399</y><x>397</x><d>139</d><cT>Platform</cT><sT>29</sT></SO>
<SO><y>-1399</y><x>654</x><d>140</d><cT>Platform</cT><sT>29</sT></SO>
<SO><y>-1399</y><x>974</x><d>141</d><cT>Platform</cT><sT>30</sT></SO>
<SO><y>-1399</y><x>205</x><d>142</d><cT>Platform</cT><sT>31</sT></SO>
<SO><y>-1492</y><x>193</x><d>143</d><cT>Trap</cT><sT>11</sT></SO>
<SO><y>-1400</y><x>324</x><d>144</d><cT>Hazard</cT><sT>4</sT></SO>
<SO><addProps><facingDir>left</facingDir></addProps><y>-1447</y><x>488</x><d>145</d><cT>Enemy</cT><sT>9</sT></SO>
<SO><addProps><facingDir>left</facingDir></addProps><y>-1447</y><x>528</x><d>146</d><cT>Enemy</cT><sT>9</sT></SO>
<SO><addProps><facingDir>left</facingDir></addProps><y>-1466</y><x>509</x><d>147</d><cT>Enemy</cT><sT>9</sT></SO>
<SO><addProps><facingDir>left</facingDir></addProps><y>-1485</y><x>469</x><d>148</d><cT>Enemy</cT><sT>9</sT></SO>
<SO><addProps><facingDir>left</facingDir></addProps><y>-1485</y><x>549</x><d>149</d><cT>Enemy</cT><sT>9</sT></SO>
<SO><addProps><facingDir>left</facingDir></addProps><y>-1485</y><x>509</x><d>150</d><cT>Enemy</cT><sT>9</sT></SO>
<SO><addProps><facingDir>left</facingDir></addProps><y>-1466</y><x>469</x><d>151</d><cT>Enemy</cT><sT>9</sT></SO>
<SO><addProps><facingDir>left</facingDir></addProps><y>-1466</y><x>549</x><d>152</d><cT>Enemy</cT><sT>9</sT></SO>
<SO><addProps><shotsToFire>2</shotsToFire><facingDir>left</facingDir></addProps><y>-1399</y><x>814</x><d>153</d><cT>Enemy</cT><sT>12</sT></SO>
<SO><addProps><facingDir>left</facingDir></addProps><y>-1073</y><x>534</x><d>154</d><cT>Enemy</cT><sT>9</sT></SO>
<SO><y>-1040</y><x>376</x><d>155</d><cT>Hazard</cT><sT>4</sT></SO>
<SO><y>-1040</y><x>479</x><d>156</d><cT>Hazard</cT><sT>4</sT></SO>
<SO><y>-1040</y><x>591</x><d>157</d><cT>Hazard</cT><sT>4</sT></SO>
<SO><addProps><facingDir>left</facingDir></addProps><y>-1071</y><x>325</x><d>158</d><cT>Enemy</cT><sT>9</sT></SO>
<SO><addProps><shotsToFire>5</shotsToFire><facingDir>left</facingDir></addProps><y>-1039</y><x>647</x><d>159</d><cT>Enemy</cT><sT>12</sT></SO>
<SO><y>-1409</y><x>415</x><d>160</d><cT>Powerup</cT><sT>0</sT></SO>
<SO><addProps><facingDir>left</facingDir></addProps><y>-1399</y><x>412</x><d>161</d><cT>Enemy</cT><sT>4</sT></SO>
<SO><y>-1432</y><x>682</x><d>162</d><cT>Trap</cT><sT>10</sT></SO>
<SO><addProps><facingDir>left</facingDir></addProps><y>-679</y><x>272</x><d>163</d><cT>Enemy</cT><sT>26</sT></SO>
<SO><y>-1049</y><x>434</x><d>164</d><cT>Powerup</cT><sT>0</sT></SO>
<SO><y>-673</y><x>826</x><d>165</d><cT>Trap</cT><sT>4</sT></SO>
<SO><y>-1399</y><x>846</x><d>166</d><cT>Platform</cT><sT>28</sT></SO>
<SO><y>-1375</y><x>974</x><d>167</d><cT>Platform</cT><sT>29</sT></SO>
<SO><y>-1375</y><x>974</x><d>168</d><cT>Platform</cT><sT>31</sT></SO>
<SO><y>-1375</y><x>1166</x><d>169</d><cT>Platform</cT><sT>30</sT></SO>
<SO><y>-1399</y><x>1166</x><d>170</d><cT>Platform</cT><sT>31</sT></SO>
<SO><y>-1399</y><x>1166</x><d>171</d><cT>Platform</cT><sT>29</sT></SO>
<SO><y>-1399</y><x>1358</x><d>172</d><cT>Platform</cT><sT>30</sT></SO>
<SO><y>-1375</y><x>995</x><d>173</d><cT>Hazard</cT><sT>0</sT></SO>
<SO><y>-1375</y><x>1125</x><d>174</d><cT>Hazard</cT><sT>0</sT></SO>
<SO><y>-1375</y><x>1107</x><d>175</d><cT>Hazard</cT><sT>0</sT></SO>
<SO><y>-1375</y><x>1089</x><d>176</d><cT>Hazard</cT><sT>0</sT></SO>
<SO><y>-1375</y><x>1071</x><d>177</d><cT>Hazard</cT><sT>0</sT></SO>
<SO><y>-1375</y><x>1053</x><d>178</d><cT>Hazard</cT><sT>0</sT></SO>
<SO><y>-1375</y><x>1035</x><d>179</d><cT>Hazard</cT><sT>0</sT></SO>
<SO><y>-1375</y><x>1017</x><d>180</d><cT>Hazard</cT><sT>0</sT></SO>
<SO><y>-1375</y><x>1143</x><d>181</d><cT>Hazard</cT><sT>0</sT></SO>
<SO><y>-1408</y><x>1008</x><d>182</d><cT>Trap</cT><sT>10</sT></SO>
<SO><y>-1408</y><x>1062</x><d>183</d><cT>Trap</cT><sT>10</sT></SO>
<SO><y>-1408</y><x>1033</x><d>184</d><cT>Trap</cT><sT>10</sT></SO>
<SO><y>-1444</y><x>971</x><d>185</d><cT>Platform</cT><sT>30</sT></SO>
<SO><y>-1444</y><x>971</x><d>186</d><cT>Platform</cT><sT>31</sT></SO>
<SO><y>-1486</y><x>1020</x><d>187</d><cT>Platform</cT><sT>30</sT></SO>
<SO><y>-1486</y><x>1020</x><d>188</d><cT>Platform</cT><sT>31</sT></SO>
<SO><y>-1529</y><x>1072</x><d>189</d><cT>Platform</cT><sT>30</sT></SO>
<SO><y>-1529</y><x>1072</x><d>190</d><cT>Platform</cT><sT>31</sT></SO>
<SO><y>-1486</y><x>1111</x><d>191</d><cT>Platform</cT><sT>30</sT></SO>
<SO><y>-1486</y><x>1111</x><d>192</d><cT>Platform</cT><sT>31</sT></SO>
<SO><y>-1445</y><x>1164</x><d>193</d><cT>Platform</cT><sT>30</sT></SO>
<SO><y>-1445</y><x>1164</x><d>194</d><cT>Platform</cT><sT>31</sT></SO>
<SO><y>-1527</y><x>1072</x><d>195</d><cT>Trap</cT><sT>2</sT></SO>
<SO><y>-1399</y><x>944</x><d>196</d><cT>Hazard</cT><sT>4</sT></SO>
<SO><y>-1399</y><x>1190</x><d>197</d><cT>Hazard</cT><sT>4</sT></SO>
<SO><y>-1398</y><x>1251</x><d>198</d><cT>Goal</cT><sT>0</sT></SO>
<SO><y>-1398</y><x>1263</x><d>199</d><cT>Ornament</cT><sT>5</sT></SO>
<SO><y>-1398</y><x>1329</x><d>200</d><cT>Ornament</cT><sT>5</sT></SO>
<SO><y>-1398</y><x>1296</x><d>201</d><cT>Ornament</cT><sT>5</sT></SO>
<SO><y>-1496</y><x>1026</x><d>202</d><cT>Powerup</cT><sT>0</sT></SO>
<SO><y>-1399</y><x>657</x><d>203</d><cT>Platform</cT><sT>31</sT></SO>
<SO><y>-1399</y><x>589</x><d>204</d><cT>Platform</cT><sT>30</sT></SO>
<SO><y>-1399</y><x>589</x><d>205</d><cT>Platform</cT><sT>19</sT></SO>
<SO><addProps><facingDir>left</facingDir></addProps><y>-565</y><x>147</x><d>206</d><cT>Enemy</cT><sT>40</sT></SO>
<SO><addProps><facingDir>left</facingDir></addProps><y>-1518</y><x>1072</x><d>207</d><cT>Enemy</cT><sT>41</sT></SO>
<levelProperties><bkgrdA>8</bkgrdA><playerStartY>193</playerStartY><playerStartX>24</playerStartX><ScrollLockY>false</ScrollLockY><ScrollLockX>false</ScrollLockX></levelProperties>
