<SO><y>129</y><x>50</x><d>0</d><cT>Ornament</cT><sT>2</sT></SO>
<SO><y>129</y><x>159</x><d>1</d><cT>Ornament</cT><sT>2</sT></SO>
<SO><y>129</y><x>101</x><d>2</d><cT>Ornament</cT><sT>2</sT></SO>
<SO><y>170</y><x>50</x><d>3</d><cT>Ornament</cT><sT>2</sT></SO>
<SO><y>170</y><x>159</x><d>4</d><cT>Ornament</cT><sT>2</sT></SO>
<SO><y>170</y><x>101</x><d>5</d><cT>Ornament</cT><sT>2</sT></SO>
<SO><y>207</y><x>50</x><d>6</d><cT>Ornament</cT><sT>2</sT></SO>
<SO><y>207</y><x>159</x><d>7</d><cT>Ornament</cT><sT>2</sT></SO>
<SO><y>207</y><x>101</x><d>8</d><cT>Ornament</cT><sT>2</sT></SO>
<SO><y>306</y><x>42</x><d>9</d><cT>Ornament</cT><sT>0</sT></SO>
<SO><y>306</y><x>101</x><d>10</d><cT>Ornament</cT><sT>0</sT></SO>
<SO><y>306</y><x>159</x><d>11</d><cT>Ornament</cT><sT>0</sT></SO>
<SO><y>306</y><x>0</x><d>12</d><cT>Platform</cT><sT>9</sT></SO>
<SO><y>306</y><x>196</x><d>13</d><cT>Platform</cT><sT>9</sT></SO>
<SO><y>308</y><x>348</x><d>14</d><cT>Trap</cT><sT>2</sT></SO>
<SO><y>196</y><x>348</x><d>15</d><cT>Trap</cT><sT>5</sT></SO>
<SO><y>50</y><x>342</x><d>16</d><cT>Wall</cT><sT>0</sT></SO>
<SO><y>-94</y><x>342</x><d>17</d><cT>Wall</cT><sT>0</sT></SO>
<SO><y>35</y><x>401</x><d>18</d><cT>Wall</cT><sT>0</sT></SO>
<SO><y>234</y><x>359</x><d>19</d><cT>Ladder</cT><sT>1</sT></SO>
<SO><y>162</y><x>359</x><d>20</d><cT>Ladder</cT><sT>1</sT></SO>
<SO><y>158</y><x>402</x><d>21</d><cT>Wall</cT><sT>0</sT></SO>
<SO><y>-97</y><x>401</x><d>22</d><cT>Wall</cT><sT>0</sT></SO>
<SO><y>90</y><x>359</x><d>23</d><cT>Ladder</cT><sT>1</sT></SO>
<SO><y>18</y><x>359</x><d>24</d><cT>Ladder</cT><sT>1</sT></SO>
<SO><y>-54</y><x>359</x><d>25</d><cT>Ladder</cT><sT>1</sT></SO>
<SO><y>-54</y><x>344</x><d>26</d><cT>Platform</cT><sT>18</sT></SO>
<SO><y>-54</y><x>408</x><d>27</d><cT>Platform</cT><sT>10</sT></SO>
<SO><y>-54</y><x>344</x><d>28</d><cT>Platform</cT><sT>11</sT></SO>
<SO><y>-90</y><x>347</x><d>29</d><cT>Hazard</cT><sT>4</sT></SO>
<SO><addProps><off_x>48</off_x><off_y>41</off_y></addProps><y>-103</y><x>386</x><d>30</d><cT>WarpPad</cT><sT>0</sT></SO>
<SO><y>-54</y><x>426</x><d>31</d><cT>Platform</cT><sT>1</sT></SO>
<SO><y>-54</y><x>432</x><d>32</d><cT>Platform</cT><sT>2</sT></SO>
<SO><y>-15</y><x>478</x><d>33</d><cT>Platform</cT><sT>1</sT></SO>
<SO><y>-15</y><x>484</x><d>34</d><cT>Platform</cT><sT>2</sT></SO>
<SO><y>33</y><x>426</x><d>35</d><cT>Platform</cT><sT>1</sT></SO>
<SO><y>33</y><x>432</x><d>36</d><cT>Platform</cT><sT>2</sT></SO>
<SO><y>61</y><x>478</x><d>37</d><cT>Platform</cT><sT>1</sT></SO>
<SO><y>61</y><x>484</x><d>38</d><cT>Platform</cT><sT>2</sT></SO>
<SO><y>115</y><x>426</x><d>39</d><cT>Platform</cT><sT>1</sT></SO>
<SO><y>115</y><x>432</x><d>40</d><cT>Platform</cT><sT>2</sT></SO>
<SO><addProps><maxVelX>1</maxVelX><rRange>100</rRange><facingDir>left</facingDir></addProps><y>33</y><x>426</x><d>41</d><cT>Enemy</cT><sT>6</sT></SO>
<SO><addProps><facingDir>left</facingDir></addProps><y>115</y><x>439</x><d>42</d><cT>Enemy</cT><sT>23</sT></SO>
<SO><y>296</y><x>490</x><d>43</d><cT>Powerup</cT><sT>0</sT></SO>
<SO><addProps><facingDir>left</facingDir></addProps><y>61</y><x>495</x><d>44</d><cT>Enemy</cT><sT>21</sT></SO>
<SO><addProps><facingDir>left</facingDir></addProps><y>306</y><x>375</x><d>45</d><cT>Enemy</cT><sT>17</sT></SO>
<SO><addProps><facingDir>left</facingDir></addProps><y>306</y><x>315</x><d>46</d><cT>Enemy</cT><sT>4</sT></SO>
<SO><addProps><facingDir>left</facingDir></addProps><y>306</y><x>262</x><d>47</d><cT>Enemy</cT><sT>4</sT></SO>
<SO><addProps><facingDir>left</facingDir></addProps><y>306</y><x>209</x><d>48</d><cT>Enemy</cT><sT>4</sT></SO>
<SO><addProps><facingDir>left</facingDir></addProps><y>306</y><x>156</x><d>49</d><cT>Enemy</cT><sT>4</sT></SO>
<SO><addProps><facingDir>left</facingDir></addProps><y>306</y><x>108</x><d>50</d><cT>Enemy</cT><sT>8</sT></SO>
<SO><addProps><facingDir>left</facingDir><velX>-3</velX><velY>0</velY></addProps><y>274</y><x>457</x><d>51</d><cT>Enemy</cT><sT>30</sT></SO>
<SO><addProps><facingDir>left</facingDir></addProps><y>232</y><x>376</x><d>52</d><cT>Enemy</cT><sT>9</sT></SO>
<SO><addProps><facingDir>left</facingDir></addProps><y>-54</y><x>426</x><d>53</d><cT>Enemy</cT><sT>0</sT></SO>
<SO><y>306</y><x>404</x><d>54</d><cT>Platform</cT><sT>43</sT></SO>
<SO><y>306</y><x>488</x><d>55</d><cT>Platform</cT><sT>43</sT></SO>
<SO><y>306</y><x>572</x><d>56</d><cT>Platform</cT><sT>43</sT></SO>
<SO><y>306</y><x>357</x><d>57</d><cT>Platform</cT><sT>9</sT></SO>
<SO><y>306</y><x>656</x><d>58</d><cT>Platform</cT><sT>43</sT></SO>
<SO><y>306</y><x>740</x><d>59</d><cT>Platform</cT><sT>43</sT></SO>
<SO><y>306</y><x>553</x><d>60</d><cT>Platform</cT><sT>9</sT></SO>
<SO><y>306</y><x>625</x><d>61</d><cT>Platform</cT><sT>9</sT></SO>
<SO><addProps><off_x>18</off_x><off_y>-378</off_y></addProps><y>306</y><x>781</x><d>62</d><cT>WarpPad</cT><sT>0</sT></SO>
<SO><y>-3</y><x>817</x><d>63</d><cT>Hazard</cT><sT>3</sT></SO>
<SO><y>-62</y><x>765</x><d>64</d><cT>Obstacle</cT><sT>3</sT></SO>
<SO><y>305</y><x>639</x><d>65</d><cT>Hazard</cT><sT>4</sT></SO>
<SO><y>305</y><x>458</x><d>66</d><cT>Hazard</cT><sT>5</sT></SO>
<SO><y>166</y><x>822</x><d>67</d><cT>Wall</cT><sT>0</sT></SO>
<SO><y>22</y><x>822</x><d>68</d><cT>Wall</cT><sT>0</sT></SO>
<SO><y>306</y><x>821</x><d>69</d><cT>Platform</cT><sT>10</sT></SO>
<SO><y>-96</y><x>833</x><d>70</d><cT>Obstacle</cT><sT>2</sT></SO>
<SO><y>-32</y><x>837</x><d>71</d><cT>Obstacle</cT><sT>0</sT></SO>
<SO><y>20</y><x>837</x><d>72</d><cT>Obstacle</cT><sT>0</sT></SO>
<SO><y>280</y><x>837</x><d>73</d><cT>Obstacle</cT><sT>0</sT></SO>
<SO><y>228</y><x>837</x><d>74</d><cT>Obstacle</cT><sT>0</sT></SO>
<SO><y>176</y><x>837</x><d>75</d><cT>Obstacle</cT><sT>0</sT></SO>
<SO><y>124</y><x>837</x><d>76</d><cT>Obstacle</cT><sT>0</sT></SO>
<SO><y>72</y><x>837</x><d>77</d><cT>Obstacle</cT><sT>0</sT></SO>
<SO><y>332</y><x>837</x><d>78</d><cT>Obstacle</cT><sT>0</sT></SO>
<SO><y>-243</y><x>743</x><d>79</d><cT>Obstacle</cT><sT>4</sT></SO>
<SO><addProps><facingDir>left</facingDir></addProps><y>-95</y><x>864</x><d>80</d><cT>Enemy</cT><sT>8</sT></SO>
<SO><y>-82</y><x>900</x><d>81</d><cT>Platform</cT><sT>43</sT></SO>
<SO><y>0</y><x>948</x><d>82</d><cT>Platform</cT><sT>42</sT></SO>
<SO><y>82</y><x>900</x><d>83</d><cT>Platform</cT><sT>43</sT></SO>
<SO><y>164</y><x>948</x><d>84</d><cT>Platform</cT><sT>42</sT></SO>
<SO><y>230</y><x>900</x><d>85</d><cT>Platform</cT><sT>43</sT></SO>
<SO><y>312</y><x>948</x><d>86</d><cT>Platform</cT><sT>42</sT></SO>
<SO><addProps><facingDir>left</facingDir></addProps><y>73</y><x>869</x><d>87</d><cT>Enemy</cT><sT>4</sT></SO>
<SO><addProps><facingDir>left</facingDir></addProps><y>177</y><x>864</x><d>88</d><cT>Enemy</cT><sT>40</sT></SO>
<SO><addProps><facingDir>left</facingDir></addProps><y>-170</y><x>897</x><d>89</d><cT>Enemy</cT><sT>20</sT></SO>
<SO><addProps><maxVelX>4</maxVelX><rRange>100</rRange><facingDir>left</facingDir></addProps><y>0</y><x>970</x><d>90</d><cT>Enemy</cT><sT>6</sT></SO>
<SO><addProps><facingDir>left</facingDir></addProps><y>71</y><x>1037</x><d>91</d><cT>Enemy</cT><sT>23</sT></SO>
<SO><y>345</y><x>905</x><d>92</d><cT>Hazard</cT><sT>0</sT></SO>
<SO><y>345</y><x>923</x><d>93</d><cT>Hazard</cT><sT>0</sT></SO>
<SO><y>345</y><x>941</x><d>94</d><cT>Hazard</cT><sT>0</sT></SO>
<SO><y>77</y><x>1004</x><d>95</d><cT>Powerup</cT><sT>0</sT></SO>
<SO><y>164</y><x>996</x><d>96</d><cT>Trap</cT><sT>0</sT></SO>
<SO><y>-32</y><x>779</x><d>97</d><cT>LavaFall</cT><sT>0</sT></SO>
<SO><y>-128</y><x>1029</x><d>98</d><cT>Wall</cT><sT>0</sT></SO>
<SO><y>-272</y><x>1029</x><d>99</d><cT>Wall</cT><sT>0</sT></SO>
<SO><y>16</y><x>1029</x><d>100</d><cT>Wall</cT><sT>0</sT></SO>
<SO><y>105</y><x>1029</x><d>101</d><cT>Wall</cT><sT>0</sT></SO>
<SO><y>230</y><x>959</x><d>102</d><cT>Trap</cT><sT>1</sT></SO>
<SO><y>247</y><x>904</x><d>103</d><cT>Trap</cT><sT>5</sT></SO>
<SO><y>247</y><x>914</x><d>104</d><cT>Trap</cT><sT>5</sT></SO>
<SO><y>247</y><x>924</x><d>105</d><cT>Trap</cT><sT>5</sT></SO>
<SO><y>247</y><x>934</x><d>106</d><cT>Trap</cT><sT>5</sT></SO>
<SO><y>247</y><x>944</x><d>107</d><cT>Trap</cT><sT>5</sT></SO>
<SO><y>247</y><x>973</x><d>108</d><cT>Trap</cT><sT>5</sT></SO>
<SO><y>247</y><x>954</x><d>109</d><cT>Trap</cT><sT>5</sT></SO>
<SO><y>247</y><x>964</x><d>110</d><cT>Trap</cT><sT>5</sT></SO>
<SO><y>306</y><x>1040</x><d>111</d><cT>Platform</cT><sT>9</sT></SO>
<SO><y>306</y><x>1040</x><d>112</d><cT>Platform</cT><sT>11</sT></SO>
<SO><y>306</y><x>1236</x><d>113</d><cT>Platform</cT><sT>9</sT></SO>
<SO><addProps><shotsToFire>1</shotsToFire><facingDir>right</facingDir></addProps><y>306</y><x>1072</x><d>114</d><cT>Enemy</cT><sT>12</sT></SO>
<SO><addProps><shotsToFire>1</shotsToFire><facingDir>right</facingDir></addProps><y>306</y><x>1126</x><d>115</d><cT>Enemy</cT><sT>12</sT></SO>
<SO><addProps><shotsToFire>1</shotsToFire><facingDir>right</facingDir></addProps><y>306</y><x>1180</x><d>116</d><cT>Enemy</cT><sT>12</sT></SO>
<SO><addProps><shotsToFire>1</shotsToFire><facingDir>right</facingDir></addProps><y>306</y><x>1234</x><d>117</d><cT>Enemy</cT><sT>12</sT></SO>
<SO><addProps><facingDir>left</facingDir></addProps><y>370</y><x>1112</x><d>118</d><cT>Enemy</cT><sT>14</sT></SO>
<SO><addProps><facingDir>left</facingDir></addProps><y>370</y><x>1222</x><d>119</d><cT>Enemy</cT><sT>14</sT></SO>
<SO><addProps><facingDir>left</facingDir></addProps><y>370</y><x>1332</x><d>120</d><cT>Enemy</cT><sT>14</sT></SO>
<SO><y>230</y><x>921</x><d>121</d><cT>Trap</cT><sT>1</sT></SO>
<SO><addProps><shotsToFire>10</shotsToFire><facingDir>right</facingDir></addProps><y>314</y><x>773</x><d>122</d><cT>Enemy</cT><sT>12</sT></SO>
<SO><y>-201</y><x>748</x><d>123</d><cT>Trap</cT><sT>5</sT></SO>
<SO><y>-201</y><x>758</x><d>124</d><cT>Trap</cT><sT>5</sT></SO>
<SO><y>-201</y><x>768</x><d>125</d><cT>Trap</cT><sT>5</sT></SO>
<SO><y>-201</y><x>778</x><d>126</d><cT>Trap</cT><sT>5</sT></SO>
<SO><y>-201</y><x>788</x><d>127</d><cT>Trap</cT><sT>5</sT></SO>
<SO><y>-201</y><x>798</x><d>128</d><cT>Trap</cT><sT>5</sT></SO>
<SO><y>-201</y><x>808</x><d>129</d><cT>Trap</cT><sT>5</sT></SO>
<SO><y>-201</y><x>818</x><d>130</d><cT>Trap</cT><sT>5</sT></SO>
<SO><y>-201</y><x>828</x><d>131</d><cT>Trap</cT><sT>5</sT></SO>
<SO><y>-201</y><x>838</x><d>132</d><cT>Trap</cT><sT>5</sT></SO>
<SO><y>-201</y><x>848</x><d>133</d><cT>Trap</cT><sT>5</sT></SO>
<SO><y>-201</y><x>858</x><d>134</d><cT>Trap</cT><sT>5</sT></SO>
<SO><y>-201</y><x>868</x><d>135</d><cT>Trap</cT><sT>5</sT></SO>
<SO><y>306</y><x>1432</x><d>136</d><cT>Platform</cT><sT>9</sT></SO>
<SO><y>273</y><x>535</x><d>137</d><cT>Trap</cT><sT>10</sT></SO>
<SO><y>-203</y><x>755</x><d>138</d><cT>Trap</cT><sT>8</sT></SO>
<SO><y>318</y><x>991</x><d>139</d><cT>Trap</cT><sT>4</sT></SO>
<SO><y>215</y><x>1297</x><d>140</d><cT>Trap</cT><sT>6</sT></SO>
<SO><y>297</y><x>1540</x><d>141</d><cT>Powerup</cT><sT>0</sT></SO>
<SO><y>306</y><x>1627</x><d>142</d><cT>Platform</cT><sT>9</sT></SO>
<SO><y>306</y><x>1823</x><d>143</d><cT>Platform</cT><sT>9</sT></SO>
<SO><y>306</y><x>2019</x><d>144</d><cT>Platform</cT><sT>9</sT></SO>
<SO><y>306</y><x>2215</x><d>145</d><cT>Platform</cT><sT>9</sT></SO>
<SO><y>306</y><x>2411</x><d>146</d><cT>Platform</cT><sT>9</sT></SO>
<SO><y>306</y><x>2607</x><d>147</d><cT>Platform</cT><sT>9</sT></SO>
<SO><y>306</y><x>2803</x><d>148</d><cT>Platform</cT><sT>9</sT></SO>
<SO><y>306</y><x>2999</x><d>149</d><cT>Platform</cT><sT>9</sT></SO>
<SO><y>306</y><x>2321</x><d>150</d><cT>Goal</cT><sT>0</sT></SO>
<SO><y>215</y><x>1351</x><d>151</d><cT>Trap</cT><sT>6</sT></SO>
<SO><y>215</y><x>1328</x><d>152</d><cT>Trap</cT><sT>6</sT></SO>
<SO><y>215</y><x>1387</x><d>153</d><cT>Trap</cT><sT>6</sT></SO>
<SO><y>215</y><x>1432</x><d>154</d><cT>Trap</cT><sT>6</sT></SO>
<SO><y>215</y><x>1407</x><d>155</d><cT>Trap</cT><sT>6</sT></SO>
<SO><y>215</y><x>1367</x><d>156</d><cT>Trap</cT><sT>6</sT></SO>
<SO><y>215</y><x>1457</x><d>157</d><cT>Trap</cT><sT>6</sT></SO>
<SO><y>215</y><x>1314</x><d>158</d><cT>Trap</cT><sT>6</sT></SO>
<SO><y>215</y><x>1368</x><d>159</d><cT>Trap</cT><sT>6</sT></SO>
<SO><y>215</y><x>1345</x><d>160</d><cT>Trap</cT><sT>6</sT></SO>
<SO><y>215</y><x>1404</x><d>161</d><cT>Trap</cT><sT>6</sT></SO>
<SO><y>215</y><x>1449</x><d>162</d><cT>Trap</cT><sT>6</sT></SO>
<SO><y>215</y><x>1424</x><d>163</d><cT>Trap</cT><sT>6</sT></SO>
<SO><y>215</y><x>1384</x><d>164</d><cT>Trap</cT><sT>6</sT></SO>
<SO><y>215</y><x>1474</x><d>165</d><cT>Trap</cT><sT>6</sT></SO>
<SO><y>216</y><x>1272</x><d>166</d><cT>Trap</cT><sT>6</sT></SO>
<SO><y>216</y><x>1326</x><d>167</d><cT>Trap</cT><sT>6</sT></SO>
<SO><y>216</y><x>1303</x><d>168</d><cT>Trap</cT><sT>6</sT></SO>
<SO><y>216</y><x>1362</x><d>169</d><cT>Trap</cT><sT>6</sT></SO>
<SO><y>216</y><x>1407</x><d>170</d><cT>Trap</cT><sT>6</sT></SO>
<SO><y>216</y><x>1382</x><d>171</d><cT>Trap</cT><sT>6</sT></SO>
<SO><y>216</y><x>1342</x><d>172</d><cT>Trap</cT><sT>6</sT></SO>
<SO><y>216</y><x>1432</x><d>173</d><cT>Trap</cT><sT>6</sT></SO>
<levelProperties><bkgrdA>1</bkgrdA><playerStartY>306</playerStartY><playerStartX>23</playerStartX><ScrollLockY>false</ScrollLockY><ScrollLockX>false</ScrollLockX></levelProperties>
